locusselect/config.py
locusselect/custom_losses.py
locusselect/generators.py
locusselect/metrics.py
locusselect/utils.py
locusselect/deeplift/__init__.py
locusselect/dist/__init__.py
locusselect/embeddings/__init__.py
locusselect/gapped_kmers/__init__.py
locusselect/vis/__init__.py
locusselect-0.3.dist-info/METADATA
locusselect-0.3.dist-info/WHEEL
locusselect-0.3.dist-info/entry_points.txt
locusselect-0.3.dist-info/top_level.txt
locusselect-0.3.dist-info/RECORD
