Metadata-Version: 2.1
Name: locusselect
Version: 0.3
Summary: Compute deep learning embeddings for narrowPeak files; compute pairwise distance between embeddings and cluster with tSNE
Home-page: UNKNOWN
Author: UNKNOWN
Author-email: UNKNOWN
License: UNKNOWN
Download-URL: https://github.com/kundajelab/locusselect
Platform: UNKNOWN
Requires-Dist: numpy (>=1.9)
Requires-Dist: keras (>=2.2)
Requires-Dist: h5py
Requires-Dist: pandas
Requires-Dist: deeplift
